README.md
setup.py
autofeature/__init__.py
autofeature.egg-info/PKG-INFO
autofeature.egg-info/SOURCES.txt
autofeature.egg-info/dependency_links.txt
autofeature.egg-info/requires.txt
autofeature.egg-info/top_level.txt
autofeature/constants/__init__.py
autofeature/constants/keys.py
autofeature/constants/modes.py
autofeature/constants/ops.py
autofeature/constants/paths.py
autofeature/entities/__init__.py
autofeature/entities/entity.py
autofeature/feature_engineering/__init__.py
autofeature/feature_engineering/aggregation.py
autofeature/feature_engineering/combined.py
autofeature/feature_engineering/feature_base.py
autofeature/feature_engineering/feature_engineering_pipeline.py
autofeature/feature_engineering/one_hot_encoding.py
autofeature/feature_engineering/select.py
autofeature/feature_engineering/text_vectorization.py
autofeature/feature_engineering/tokenizer.py
autofeature/feature_engineering/transformation.py
autofeature/feature_engineering/word2vec.py
autofeature/properties/__init__.py
autofeature/properties/property.py
autofeature/utils/__init__.py
autofeature/utils/log_handler.py