Metadata-Version: 1.0
Name: autofeature
Version: 0.1
Summary: a library to automate feature engineering
Home-page: UNKNOWN
Author: Jing Y.
Author-email: joyceye04@gmail.com
License: UNKNOWN
Keywords: FeatureEngineering
Platform: UNKNOWN
